aresti_django.py
python_aresti_django-0.1.dist-info/METADATA
python_aresti_django-0.1.dist-info/WHEEL
python_aresti_django-0.1.dist-info/historia.json
python_aresti_django-0.1.dist-info/top_level.txt
python_aresti_django-0.1.dist-info/RECORD
